odoo10_addon_delivery_price_by_category-10.0.1.0.0.99.dev6-py3.8-nspkg.pth
odoo/addons/delivery_price_by_category/README.rst
odoo/addons/delivery_price_by_category/__init__.py
odoo/addons/delivery_price_by_category/__manifest__.py
odoo/addons/delivery_price_by_category/i18n/delivery_price_by_category.pot
odoo/addons/delivery_price_by_category/i18n/it.po
odoo/addons/delivery_price_by_category/models/__init__.py
odoo/addons/delivery_price_by_category/models/delivery_carrier.py
odoo/addons/delivery_price_by_category/models/delivery_price_rule.py
odoo/addons/delivery_price_by_category/readme/CONFIGURE.rst
odoo/addons/delivery_price_by_category/readme/CONTRIBUTORS.rst
odoo/addons/delivery_price_by_category/readme/DESCRIPTION.rst
odoo/addons/delivery_price_by_category/readme/USAGE.rst
odoo/addons/delivery_price_by_category/static/description/icon.png
odoo/addons/delivery_price_by_category/static/description/index.html
odoo/addons/delivery_price_by_category/tests/__init__.py
odoo/addons/delivery_price_by_category/tests/test_price_by_category.py
odoo/addons/delivery_price_by_category/views/delivery_price_rule.xml
odoo10_addon_delivery_price_by_category-10.0.1.0.0.99.dev6.dist-info/METADATA
odoo10_addon_delivery_price_by_category-10.0.1.0.0.99.dev6.dist-info/WHEEL
odoo10_addon_delivery_price_by_category-10.0.1.0.0.99.dev6.dist-info/namespace_packages.txt
odoo10_addon_delivery_price_by_category-10.0.1.0.0.99.dev6.dist-info/top_level.txt
odoo10_addon_delivery_price_by_category-10.0.1.0.0.99.dev6.dist-info/RECORD
